codestat/__init__.py
codestat/__main__.py
codestat/codestat.py
codestat-0.1a1.dist-info/METADATA
codestat-0.1a1.dist-info/RECORD
codestat-0.1a1.dist-info/WHEEL
codestat-0.1a1.dist-info/entry_points.txt
codestat-0.1a1.dist-info/top_level.txt
