Metadata-Version: 2.1
Name: codestat
Version: 0.1a1
Summary: Generate statistics about your code.
Home-page: https://github.com/dexpota/codestat
Author: Fabrizio Destro
Author-email: destro.fabrizio@gmail.com
License: UNKNOWN
Platform: UNKNOWN
Classifier: Development Status :: 3 - Alpha
Classifier: Intended Audience :: Developers
Classifier: Programming Language :: Python :: 3
Requires-Dist: pyyaml
